{
    "$id": "https://schema.hagleitner.com/bdim/2026-06-01/customer.schema.json",
    "$schema": "https://json-schema.org/draft/2020-12/schema",
    "description": "Customer",
    "type": "object",
    "unevaluatedProperties": false,
    "required": [
        "id",
        "name1",
        "status",
        "customerRelations",
        "contentHash"
    ],
    "properties": {
        "id": {
            "$ref": "../components/basetypes.schema.json#/$defs/uuid"
        },
        "erpCustomerId": {
            "type": "string",
            "pattern": "^[A-Z0-9]{1,20}$"
        },
        "name1": {
            "$ref": "../components/basetypes.schema.json#/$defs/singleLineText",
            "maxLength": 100
        },
        "name2": {
            "$ref": "../components/basetypes.schema.json#/$defs/singleLineText",
            "maxLength": 50
        },
        "name3": {
            "$ref": "../components/basetypes.schema.json#/$defs/singleLineText",
            "maxLength": 30
        },
        "phoneNumber1": {
            "$ref": "../components/basetypes.schema.json#/$defs/phoneE164",
            "description": "Phone number 1"
        },
        "phoneNumber2": {
            "$ref": "../components/basetypes.schema.json#/$defs/phoneE164",
            "description": "Phone number 2"
        },
        "status": {
            "type": "string",
            "enum": ["active", "deleted"],
            "description": "The status of the customer"
        },
        "roles": {
            "type": "array",
            "items": { "type": "string", "enum": ["reseller", "invoiceRecipient", "hierarchyParent", "responsibilityCenter", "conditionOwner"] },
            "uniqueItems": true,
            "description": "Roles assigned to the customer",
            "minItems": 1
        },
        "customerRelations": {
            "type": "object",
            "unevaluatedProperties": false,
            "required": [
                "reseller"
            ],
            "properties": {
                "reseller": {
                    "type": "object",
                    "unevaluatedProperties": false,
                    "required": ["anchestorCustomerId"],
                    "properties": {
                        "anchestorCustomerId": {
                            "oneOf": [
                                { "$ref": "../components/basetypes.schema.json#/$defs/uuid" },
                                { "type": "null" }
                            ]
                        },
                        "erpTenantId": {
                            "$ref": "../components/basetypes.schema.json#/$defs/uuid"
                        }
                    }
                },
                "invoice": {
                    "type": "object",
                    "unevaluatedProperties": false,
                    "required": ["anchestorCustomerId"],
                    "properties": {
                        "anchestorCustomerId": { "$ref": "../components/basetypes.schema.json#/$defs/uuid" }
                    }
                },
                "condition": {
                    "type": "object",
                    "unevaluatedProperties": false,
                    "required": ["anchestorCustomerId"],
                    "properties": {
                        "anchestorCustomerId": { "$ref": "../components/basetypes.schema.json#/$defs/uuid" }
                    }
                },
                "hierarchy": {
                    "type": "object",
                    "unevaluatedProperties": false,
                    "required": ["anchestorCustomerId"],
                    "properties": {
                        "anchestorCustomerId": { "$ref": "../components/basetypes.schema.json#/$defs/uuid" }
                    }
                }
            }
        },
        "emailAddresses": {
            "type": "object",
            "properties": {
                "primary": { "$ref": "../components/basetypes.schema.json#/$defs/email" },
                "orderConfirmation":   { "$ref": "../components/basetypes.schema.json#/$defs/email" },
                "invoice": { "$ref": "../components/basetypes.schema.json#/$defs/email" },
                "invoiceCc": { "$ref": "../components/basetypes.schema.json#/$defs/email" },
                "paymentReminder": { "$ref": "../components/basetypes.schema.json#/$defs/email" },
                "paymentReminderCc": { "$ref": "../components/basetypes.schema.json#/$defs/email"},
                "shippingAdvice": { "$ref": "../components/basetypes.schema.json#/$defs/email"}
            },
            "unevaluatedProperties": false,
            "minProperties": 1
        },
        "contentHash": {
            "$ref": "../components/basetypes.schema.json#/$defs/contentHash"
        }
    },
    "dependentRequired": {
        "name2": [
            "name1"
        ],
        "name3": [
            "name2",
            "name1"
        ]
    },
    "allOf": [
        {
            "$ref": "../components/address.schema.json"
        }
    ]
}